[{"Year":2016,"Country":"Malaysia","Expense (% of GDP)":16.76,"Rank":2.0,"Flag":"https:\/\/GlobalArtInc.github.io\/round-flags\/flags\/my.svg"},{"Year":2017,"Country":"Malaysia","Expense (% of GDP)":15.83,"Rank":2.0,"Flag":"https:\/\/GlobalArtInc.github.io\/round-flags\/flags\/my.svg"},{"Year":2018,"Country":"Malaysia","Expense (% of GDP)":15.92,"Rank":2.0,"Flag":"https:\/\/GlobalArtInc.github.io\/round-flags\/flags\/my.svg"},{"Year":2019,"Country":"Malaysia","Expense (% of GDP)":17.36,"Rank":2.0,"Flag":"https:\/\/GlobalArtInc.github.io\/round-flags\/flags\/my.svg"},{"Year":2020,"Country":"Malaysia","Expense (% of GDP)":18.47,"Rank":4.0,"Flag":"https:\/\/GlobalArtInc.github.io\/round-flags\/flags\/my.svg"},{"Year":2021,"Country":"Malaysia","Expense (% of GDP)":17.25,"Rank":4.0,"Flag":"https:\/\/GlobalArtInc.github.io\/round-flags\/flags\/my.svg"},{"Year":2016,"Country":"Singapore","Expense (% of GDP)":14.44,"Rank":4.0,"Flag":"https:\/\/GlobalArtInc.github.io\/round-flags\/flags\/sg.svg"},{"Year":2017,"Country":"Singapore","Expense (% of GDP)":14.31,"Rank":3.0,"Flag":"https:\/\/GlobalArtInc.github.io\/round-flags\/flags\/sg.svg"},{"Year":2018,"Country":"Singapore","Expense (% of GDP)":14.69,"Rank":4.0,"Flag":"https:\/\/GlobalArtInc.github.io\/round-flags\/flags\/sg.svg"},{"Year":2019,"Country":"Singapore","Expense (% of GDP)":14.14,"Rank":6.0,"Flag":"https:\/\/GlobalArtInc.github.io\/round-flags\/flags\/sg.svg"},{"Year":2020,"Country":"Singapore","Expense (% of GDP)":25.72,"Rank":1.0,"Flag":"https:\/\/GlobalArtInc.github.io\/round-flags\/flags\/sg.svg"},{"Year":2021,"Country":"Singapore","Expense (% of GDP)":16.38,"Rank":5.0,"Flag":"https:\/\/GlobalArtInc.github.io\/round-flags\/flags\/sg.svg"},{"Year":2016,"Country":"Thailand","Expense (% of GDP)":18.58,"Rank":1.0,"Flag":"https:\/\/GlobalArtInc.github.io\/round-flags\/flags\/th.svg"},{"Year":2017,"Country":"Thailand","Expense (% of GDP)":18.1,"Rank":1.0,"Flag":"https:\/\/GlobalArtInc.github.io\/round-flags\/flags\/th.svg"},{"Year":2018,"Country":"Thailand","Expense (% of GDP)":18.05,"Rank":1.0,"Flag":"https:\/\/GlobalArtInc.github.io\/round-flags\/flags\/th.svg"},{"Year":2019,"Country":"Thailand","Expense (% of GDP)":17.6,"Rank":1.0,"Flag":"https:\/\/GlobalArtInc.github.io\/round-flags\/flags\/th.svg"},{"Year":2020,"Country":"Thailand","Expense (% of GDP)":21.67,"Rank":2.0,"Flag":"https:\/\/GlobalArtInc.github.io\/round-flags\/flags\/th.svg"},{"Year":2021,"Country":"Thailand","Expense (% of GDP)":23.87,"Rank":1.0,"Flag":"https:\/\/GlobalArtInc.github.io\/round-flags\/flags\/th.svg"},{"Year":2016,"Country":"Indonesia","Expense (% of GDP)":14.87,"Rank":3.0,"Flag":"https:\/\/GlobalArtInc.github.io\/round-flags\/flags\/id.svg"},{"Year":2017,"Country":"Indonesia","Expense (% of GDP)":14.3,"Rank":4.0,"Flag":"https:\/\/GlobalArtInc.github.io\/round-flags\/flags\/id.svg"},{"Year":2018,"Country":"Indonesia","Expense (% of GDP)":14.82,"Rank":3.0,"Flag":"https:\/\/GlobalArtInc.github.io\/round-flags\/flags\/id.svg"},{"Year":2019,"Country":"Indonesia","Expense (% of GDP)":14.49,"Rank":5.0,"Flag":"https:\/\/GlobalArtInc.github.io\/round-flags\/flags\/id.svg"},{"Year":2020,"Country":"Indonesia","Expense (% of GDP)":16.54,"Rank":6.0,"Flag":"https:\/\/GlobalArtInc.github.io\/round-flags\/flags\/id.svg"},{"Year":2021,"Country":"Indonesia","Expense (% of GDP)":15.51,"Rank":6.0,"Flag":"https:\/\/GlobalArtInc.github.io\/round-flags\/flags\/id.svg"},{"Year":2016,"Country":"Philippines","Expense (% of GDP)":13.44,"Rank":5.0,"Flag":"https:\/\/GlobalArtInc.github.io\/round-flags\/flags\/ph.svg"},{"Year":2017,"Country":"Philippines","Expense (% of GDP)":13.61,"Rank":6.0,"Flag":"https:\/\/GlobalArtInc.github.io\/round-flags\/flags\/ph.svg"},{"Year":2018,"Country":"Philippines","Expense (% of GDP)":14.21,"Rank":6.0,"Flag":"https:\/\/GlobalArtInc.github.io\/round-flags\/flags\/ph.svg"},{"Year":2019,"Country":"Philippines","Expense (% of GDP)":14.84,"Rank":4.0,"Flag":"https:\/\/GlobalArtInc.github.io\/round-flags\/flags\/ph.svg"},{"Year":2020,"Country":"Philippines","Expense (% of GDP)":19.56,"Rank":3.0,"Flag":"https:\/\/GlobalArtInc.github.io\/round-flags\/flags\/ph.svg"},{"Year":2021,"Country":"Philippines","Expense (% of GDP)":19.14,"Rank":2.0,"Flag":"https:\/\/GlobalArtInc.github.io\/round-flags\/flags\/ph.svg"},{"Year":2016,"Country":"Cambodia","Expense (% of GDP)":12.99,"Rank":6.0,"Flag":"https:\/\/GlobalArtInc.github.io\/round-flags\/flags\/kh.svg"},{"Year":2017,"Country":"Cambodia","Expense (% of GDP)":14.29,"Rank":5.0,"Flag":"https:\/\/GlobalArtInc.github.io\/round-flags\/flags\/kh.svg"},{"Year":2018,"Country":"Cambodia","Expense (% of GDP)":14.52,"Rank":5.0,"Flag":"https:\/\/GlobalArtInc.github.io\/round-flags\/flags\/kh.svg"},{"Year":2019,"Country":"Cambodia","Expense (% of GDP)":15.78,"Rank":3.0,"Flag":"https:\/\/GlobalArtInc.github.io\/round-flags\/flags\/kh.svg"},{"Year":2020,"Country":"Cambodia","Expense (% of GDP)":17.41,"Rank":5.0,"Flag":"https:\/\/GlobalArtInc.github.io\/round-flags\/flags\/kh.svg"},{"Year":2021,"Country":"Cambodia","Expense (% of GDP)":18.45,"Rank":3.0,"Flag":"https:\/\/GlobalArtInc.github.io\/round-flags\/flags\/kh.svg"}]